{
  "main": {
    "id": "8f67cf95f4546ddc",
    "type": "split",
    "children": [
      {
        "id": "2cc1973e24dc1e66",
        "type": "tabs",
        "children": [
          {
            "id": "f1df0463a49d1aa9",
            "type": "leaf",
            "state": {
              "type": "markdown",
              "state": {
                "file": "Zen/Group.md",
                "mode": "preview",
                "backlinks": false,
                "source": false
              },
              "icon": "lucide-file",
              "title": "Group"
            }
          }
        ]
      }
    ],
    "direction": "vertical"
  },
  "left": {
    "id": "2c20997869b65c2b",
    "type": "mobile-drawer",
    "children": [
      {
        "id": "ab8ff7fe6fa3c12b",
        "type": "leaf",
        "state": {
          "type": "file-explorer",
          "state": {
            "sortOrder": "alphabetical"
          },
          "icon": "lucide-folder-closed",
          "title": "Files"
        }
      },
      {
        "id": "95d9d9a40db5402c",
        "type": "leaf",
        "state": {
          "type": "search",
          "state": {
            "query": "",
            "matchingCase": false,
            "explainSearch": false,
            "collapseAll": false,
            "extraContext": false,
            "sortOrder": "alphabetical"
          },
          "icon": "lucide-search",
          "title": "Search"
        }
      },
      {
        "id": "de637665038c5cc7",
        "type": "leaf",
        "state": {
          "type": "tag",
          "state": {
            "sortOrder": "frequency",
            "useHierarchy": true
          },
          "icon": "lucide-tags",
          "title": "Tags"
        }
      },
      {
        "id": "d13db22752ce18a0",
        "type": "leaf",
        "state": {
          "type": "starred",
          "state": {},
          "icon": "lucide-file",
          "title": "Plugin no longer active"
        }
      },
      {
        "id": "5c64c70a1de7986e",
        "type": "leaf",
        "state": {
          "type": "bookmarks",
          "state": {},
          "icon": "lucide-bookmark",
          "title": "Bookmarks"
        }
      }
    ],
    "currentTab": 0
  },
  "right": {
    "id": "836965fb878e532d",
    "type": "mobile-drawer",
    "children": [
      {
        "id": "bf13feb65305cf2d",
        "type": "leaf",
        "state": {
          "type": "backlink",
          "state": {
            "file": "Timestamps/2024-11-06.md",
            "collapseAll": false,
            "extraContext": false,
            "sortOrder": "alphabetical",
            "showSearch": false,
            "searchQuery": "",
            "backlinkCollapsed": false,
            "unlinkedCollapsed": true
          },
          "icon": "links-coming-in",
          "title": "Backlinks"
        }
      },
      {
        "id": "ca4372d39bd9239a",
        "type": "leaf",
        "state": {
          "type": "outgoing-link",
          "state": {
            "file": "Zen/Group epimorphism.md",
            "linksCollapsed": false,
            "unlinkedCollapsed": true
          },
          "icon": "links-going-out",
          "title": "Outgoing links"
        }
      },
      {
        "id": "5c84379248d60034",
        "type": "leaf",
        "state": {
          "type": "outline",
          "state": {
            "file": "Zen/Group epimorphism.md"
          },
          "icon": "lucide-list",
          "title": "Outline"
        }
      },
      {
        "id": "97303d38c4511c00",
        "type": "leaf",
        "state": {
          "type": "advanced-tables-toolbar",
          "state": {},
          "icon": "spreadsheet",
          "title": "Advanced Tables"
        }
      },
      {
        "id": "04b25258a9146f9c",
        "type": "leaf",
        "state": {
          "type": "review-queue-list-view",
          "state": {},
          "icon": "SpacedRepIcon",
          "title": "Notes Review Queue"
        }
      },
      {
        "id": "f5cd5ab7e7199b99",
        "type": "leaf",
        "state": {
          "type": "calendar",
          "state": {},
          "icon": "calendar-with-checkmark",
          "title": "Calendar"
        }
      },
      {
        "id": "5ee1fe11572ddcff",
        "type": "leaf",
        "state": {
          "type": "review-queue-list-view",
          "state": {},
          "icon": "lucide-file",
          "title": "Plugin no longer active"
        }
      },
      {
        "id": "f1bfa01ef3f65241",
        "type": "leaf",
        "state": {
          "type": "review-queue-list-view",
          "state": {},
          "icon": "lucide-file",
          "title": "Plugin no longer active"
        }
      },
      {
        "id": "1f6f402e67210dbb",
        "type": "leaf",
        "state": {
          "type": "review-queue-list-view",
          "state": {},
          "icon": "lucide-file",
          "title": "Plugin no longer active"
        }
      },
      {
        "id": "9719794a0f7f4d51",
        "type": "leaf",
        "state": {
          "type": "review-queue-list-view",
          "state": {},
          "icon": "lucide-file",
          "title": "Plugin no longer active"
        }
      },
      {
        "id": "e260558d1410c080",
        "type": "leaf",
        "state": {
          "type": "review-queue-list-view",
          "state": {},
          "icon": "lucide-file",
          "title": "Plugin no longer active"
        }
      },
      {
        "id": "62f09103b91126a9",
        "type": "leaf",
        "state": {
          "type": "review-queue-list-view",
          "state": {},
          "icon": "lucide-file",
          "title": "Plugin no longer active"
        }
      },
      {
        "id": "8b15e6ca53b1fd65",
        "type": "leaf",
        "state": {
          "type": "review-queue-list-view",
          "state": {},
          "icon": "lucide-file",
          "title": "Plugin no longer active"
        }
      },
      {
        "id": "daeac0752278f013",
        "type": "leaf",
        "state": {
          "type": "review-queue-list-view",
          "state": {},
          "icon": "lucide-file",
          "title": "Plugin no longer active"
        }
      },
      {
        "id": "5f06770ef445a9fa",
        "type": "leaf",
        "state": {
          "type": "review-queue-list-view",
          "state": {},
          "icon": "lucide-file",
          "title": "Plugin no longer active"
        }
      },
      {
        "id": "40e8d8243186cedf",
        "type": "leaf",
        "state": {
          "type": "review-queue-list-view",
          "state": {},
          "icon": "lucide-file",
          "title": "Plugin no longer active"
        }
      },
      {
        "id": "a0873f3802351c6b",
        "type": "leaf",
        "state": {
          "type": "review-queue-list-view",
          "state": {},
          "icon": "lucide-file",
          "title": "Plugin no longer active"
        }
      },
      {
        "id": "fe701f2a0ef3dbea",
        "type": "leaf",
        "state": {
          "type": "review-queue-list-view",
          "state": {},
          "icon": "lucide-file",
          "title": "Plugin no longer active"
        }
      },
      {
        "id": "3d1fcec0a29c7801",
        "type": "leaf",
        "state": {
          "type": "review-queue-list-view",
          "state": {},
          "icon": "lucide-file",
          "title": "Plugin no longer active"
        }
      },
      {
        "id": "9cae3b6d4d8b0c7e",
        "type": "leaf",
        "state": {
          "type": "review-queue-list-view",
          "state": {},
          "icon": "lucide-file",
          "title": "Plugin no longer active"
        }
      },
      {
        "id": "6bbc35dd95409333",
        "type": "leaf",
        "state": {
          "type": "review-queue-list-view",
          "state": {},
          "icon": "lucide-file",
          "title": "Plugin no longer active"
        }
      },
      {
        "id": "65705c47493ab13b",
        "type": "leaf",
        "state": {
          "type": "review-queue-list-view",
          "state": {},
          "icon": "lucide-file",
          "title": "Plugin no longer active"
        }
      },
      {
        "id": "d92a1e369fc821b7",
        "type": "leaf",
        "state": {
          "type": "review-queue-list-view",
          "state": {},
          "icon": "lucide-file",
          "title": "Plugin no longer active"
        }
      },
      {
        "id": "e71cb1bb3c31f457",
        "type": "leaf",
        "state": {
          "type": "review-queue-list-view",
          "state": {},
          "icon": "lucide-file",
          "title": "Plugin no longer active"
        }
      },
      {
        "id": "3f353dc450de462a",
        "type": "leaf",
        "state": {
          "type": "review-queue-list-view",
          "state": {},
          "icon": "lucide-file",
          "title": "Plugin no longer active"
        }
      },
      {
        "id": "ae8b8564577c35f7",
        "type": "leaf",
        "state": {
          "type": "review-queue-list-view",
          "state": {},
          "icon": "lucide-file",
          "title": "Plugin no longer active"
        }
      },
      {
        "id": "064200d51784f6bf",
        "type": "leaf",
        "state": {
          "type": "review-queue-list-view",
          "state": {},
          "icon": "lucide-file",
          "title": "Plugin no longer active"
        }
      },
      {
        "id": "9e001314cd60f042",
        "type": "leaf",
        "state": {
          "type": "review-queue-list-view",
          "state": {},
          "icon": "lucide-file",
          "title": "Plugin no longer active"
        }
      },
      {
        "id": "c88ec6deace708b9",
        "type": "leaf",
        "state": {
          "type": "review-queue-list-view",
          "state": {},
          "icon": "lucide-file",
          "title": "Plugin no longer active"
        }
      },
      {
        "id": "46d7f76f844660c8",
        "type": "leaf",
        "state": {
          "type": "review-queue-list-view",
          "state": {},
          "icon": "lucide-file",
          "title": "Plugin no longer active"
        }
      },
      {
        "id": "f70251f1c0079e2d",
        "type": "leaf",
        "state": {
          "type": "review-queue-list-view",
          "state": {},
          "icon": "lucide-file",
          "title": "Plugin no longer active"
        }
      },
      {
        "id": "6f8a20a3545e364d",
        "type": "leaf",
        "state": {
          "type": "review-queue-list-view",
          "state": {},
          "icon": "lucide-file",
          "title": "Plugin no longer active"
        }
      },
      {
        "id": "e3807b739c56cbc8",
        "type": "leaf",
        "state": {
          "type": "review-queue-list-view",
          "state": {},
          "icon": "lucide-file",
          "title": "Plugin no longer active"
        }
      },
      {
        "id": "77cefae19daf54dd",
        "type": "leaf",
        "state": {
          "type": "review-queue-list-view",
          "state": {},
          "icon": "lucide-file",
          "title": "Plugin no longer active"
        }
      },
      {
        "id": "4b1967b61297d4f3",
        "type": "leaf",
        "state": {
          "type": "review-queue-list-view",
          "state": {},
          "icon": "lucide-file",
          "title": "Plugin no longer active"
        }
      },
      {
        "id": "cbbb7f2c0fd7b749",
        "type": "leaf",
        "state": {
          "type": "review-queue-list-view",
          "state": {},
          "icon": "lucide-file",
          "title": "Plugin no longer active"
        }
      },
      {
        "id": "571b2bb444c2b040",
        "type": "leaf",
        "state": {
          "type": "review-queue-list-view",
          "state": {},
          "icon": "lucide-file",
          "title": "Plugin no longer active"
        }
      },
      {
        "id": "e5327ccdc9bc7361",
        "type": "leaf",
        "state": {
          "type": "review-queue-list-view",
          "state": {},
          "icon": "lucide-file",
          "title": "Plugin no longer active"
        }
      },
      {
        "id": "1e3311c0cc81487e",
        "type": "leaf",
        "state": {
          "type": "review-queue-list-view",
          "state": {},
          "icon": "lucide-file",
          "title": "Plugin no longer active"
        }
      },
      {
        "id": "c166518133acac12",
        "type": "leaf",
        "state": {
          "type": "review-queue-list-view",
          "state": {},
          "icon": "lucide-file",
          "title": "Plugin no longer active"
        }
      },
      {
        "id": "83ed09ee84b00bd1",
        "type": "leaf",
        "state": {
          "type": "review-queue-list-view",
          "state": {},
          "icon": "lucide-file",
          "title": "Plugin no longer active"
        }
      },
      {
        "id": "717c5a9f89297a58",
        "type": "leaf",
        "state": {
          "type": "review-queue-list-view",
          "state": {},
          "icon": "lucide-file",
          "title": "Plugin no longer active"
        }
      },
      {
        "id": "ce958b08555e5263",
        "type": "leaf",
        "state": {
          "type": "review-queue-list-view",
          "state": {},
          "icon": "lucide-file",
          "title": "Plugin no longer active"
        }
      },
      {
        "id": "80d2ec857e388697",
        "type": "leaf",
        "state": {
          "type": "review-queue-list-view",
          "state": {},
          "icon": "lucide-file",
          "title": "Plugin no longer active"
        }
      },
      {
        "id": "7fcfd7bd4da78956",
        "type": "leaf",
        "state": {
          "type": "review-queue-list-view",
          "state": {},
          "icon": "lucide-file",
          "title": "Plugin no longer active"
        }
      },
      {
        "id": "69b8c51d1755a421",
        "type": "leaf",
        "state": {
          "type": "review-queue-list-view",
          "state": {},
          "icon": "lucide-file",
          "title": "Plugin no longer active"
        }
      },
      {
        "id": "bd66c8d83b85ca3c",
        "type": "leaf",
        "state": {
          "type": "review-queue-list-view",
          "state": {},
          "icon": "lucide-file",
          "title": "Plugin no longer active"
        }
      },
      {
        "id": "ca7f3b2a03ce66c7",
        "type": "leaf",
        "state": {
          "type": "review-queue-list-view",
          "state": {},
          "icon": "lucide-file",
          "title": "Plugin no longer active"
        }
      },
      {
        "id": "0f00392ed864d75e",
        "type": "leaf",
        "state": {
          "type": "review-queue-list-view",
          "state": {},
          "icon": "lucide-file",
          "title": "Plugin no longer active"
        }
      },
      {
        "id": "d132d4830a0d4258",
        "type": "leaf",
        "state": {
          "type": "review-queue-list-view",
          "state": {},
          "icon": "lucide-file",
          "title": "Plugin no longer active"
        }
      },
      {
        "id": "ebf03ce2aa9c5316",
        "type": "leaf",
        "state": {
          "type": "review-queue-list-view",
          "state": {},
          "icon": "lucide-file",
          "title": "Plugin no longer active"
        }
      },
      {
        "id": "79aa92e915aec3c1",
        "type": "leaf",
        "state": {
          "type": "review-queue-list-view",
          "state": {},
          "icon": "lucide-file",
          "title": "Plugin no longer active"
        }
      },
      {
        "id": "343286afb022e836",
        "type": "leaf",
        "state": {
          "type": "review-queue-list-view",
          "state": {},
          "icon": "lucide-file",
          "title": "Plugin no longer active"
        }
      },
      {
        "id": "91d6c99d0488173b",
        "type": "leaf",
        "state": {
          "type": "review-queue-list-view",
          "state": {},
          "icon": "lucide-file",
          "title": "Plugin no longer active"
        }
      },
      {
        "id": "c5d3b1b59da4109d",
        "type": "leaf",
        "state": {
          "type": "review-queue-list-view",
          "state": {},
          "icon": "lucide-file",
          "title": "Plugin no longer active"
        }
      },
      {
        "id": "8d7758519b573611",
        "type": "leaf",
        "state": {
          "type": "review-queue-list-view",
          "state": {},
          "icon": "lucide-file",
          "title": "Plugin no longer active"
        }
      },
      {
        "id": "d4aecc88f37daa3e",
        "type": "leaf",
        "state": {
          "type": "review-queue-list-view",
          "state": {},
          "icon": "lucide-file",
          "title": "Plugin no longer active"
        }
      },
      {
        "id": "f3c5d4e4ff178f37",
        "type": "leaf",
        "state": {
          "type": "review-queue-list-view",
          "state": {},
          "icon": "lucide-file",
          "title": "Plugin no longer active"
        }
      },
      {
        "id": "80dce14589b50f51",
        "type": "leaf",
        "state": {
          "type": "review-queue-list-view",
          "state": {},
          "icon": "lucide-file",
          "title": "Plugin no longer active"
        }
      },
      {
        "id": "af7384c37f529a6c",
        "type": "leaf",
        "state": {
          "type": "review-queue-list-view",
          "state": {},
          "icon": "lucide-file",
          "title": "Plugin no longer active"
        }
      },
      {
        "id": "6002264d6a75224d",
        "type": "leaf",
        "state": {
          "type": "review-queue-list-view",
          "state": {},
          "icon": "lucide-file",
          "title": "Plugin no longer active"
        }
      },
      {
        "id": "8931ead284ea45e8",
        "type": "leaf",
        "state": {
          "type": "review-queue-list-view",
          "state": {},
          "icon": "lucide-file",
          "title": "Plugin no longer active"
        }
      },
      {
        "id": "72fa23080961659e",
        "type": "leaf",
        "state": {
          "type": "review-queue-list-view",
          "state": {},
          "icon": "lucide-file",
          "title": "Plugin no longer active"
        }
      },
      {
        "id": "506576a490dad774",
        "type": "leaf",
        "state": {
          "type": "review-queue-list-view",
          "state": {},
          "icon": "lucide-file",
          "title": "Plugin no longer active"
        }
      },
      {
        "id": "5b0e77271917b38a",
        "type": "leaf",
        "state": {
          "type": "review-queue-list-view",
          "state": {},
          "icon": "lucide-file",
          "title": "Plugin no longer active"
        }
      },
      {
        "id": "43d51396744d942d",
        "type": "leaf",
        "state": {
          "type": "review-queue-list-view",
          "state": {},
          "icon": "lucide-file",
          "title": "Plugin no longer active"
        }
      },
      {
        "id": "13df9978abb69e32",
        "type": "leaf",
        "state": {
          "type": "review-queue-list-view",
          "state": {},
          "icon": "lucide-file",
          "title": "Plugin no longer active"
        }
      },
      {
        "id": "049eb23e481fea76",
        "type": "leaf",
        "state": {
          "type": "review-queue-list-view",
          "state": {},
          "icon": "lucide-file",
          "title": "Plugin no longer active"
        }
      },
      {
        "id": "715d2606a2a3c166",
        "type": "leaf",
        "state": {
          "type": "review-queue-list-view",
          "state": {},
          "icon": "lucide-file",
          "title": "Plugin no longer active"
        }
      },
      {
        "id": "23d4e5e5f9bbc40a",
        "type": "leaf",
        "state": {
          "type": "review-queue-list-view",
          "state": {},
          "icon": "lucide-file",
          "title": "Plugin no longer active"
        }
      },
      {
        "id": "72c01f0e2a4c150c",
        "type": "leaf",
        "state": {
          "type": "review-queue-list-view",
          "state": {},
          "icon": "lucide-file",
          "title": "Plugin no longer active"
        }
      },
      {
        "id": "df39c3c993480576",
        "type": "leaf",
        "state": {
          "type": "review-queue-list-view",
          "state": {},
          "icon": "lucide-file",
          "title": "Plugin no longer active"
        }
      },
      {
        "id": "d8b504338932f55d",
        "type": "leaf",
        "state": {
          "type": "review-queue-list-view",
          "state": {},
          "icon": "lucide-file",
          "title": "Plugin no longer active"
        }
      },
      {
        "id": "0ec08777a0794650",
        "type": "leaf",
        "state": {
          "type": "review-queue-list-view",
          "state": {},
          "icon": "lucide-file",
          "title": "Plugin no longer active"
        }
      },
      {
        "id": "2ed2a303dc79318e",
        "type": "leaf",
        "state": {
          "type": "review-queue-list-view",
          "state": {},
          "icon": "lucide-file",
          "title": "Plugin no longer active"
        }
      },
      {
        "id": "7e2921165c7ed606",
        "type": "leaf",
        "state": {
          "type": "review-queue-list-view",
          "state": {},
          "icon": "lucide-file",
          "title": "Plugin no longer active"
        }
      },
      {
        "id": "edf204d60d63fae3",
        "type": "leaf",
        "state": {
          "type": "review-queue-list-view",
          "state": {},
          "icon": "lucide-file",
          "title": "Plugin no longer active"
        }
      },
      {
        "id": "d85154f70dba6b28",
        "type": "leaf",
        "state": {
          "type": "review-queue-list-view",
          "state": {},
          "icon": "lucide-file",
          "title": "Plugin no longer active"
        }
      },
      {
        "id": "71db459cacb0f8ec",
        "type": "leaf",
        "state": {
          "type": "review-queue-list-view",
          "state": {},
          "icon": "lucide-file",
          "title": "Plugin no longer active"
        }
      },
      {
        "id": "4a1208f2b1fbba68",
        "type": "leaf",
        "state": {
          "type": "review-queue-list-view",
          "state": {},
          "icon": "lucide-file",
          "title": "Plugin no longer active"
        }
      },
      {
        "id": "cb78d6d4b19a6887",
        "type": "leaf",
        "state": {
          "type": "review-queue-list-view",
          "state": {},
          "icon": "lucide-file",
          "title": "Plugin no longer active"
        }
      },
      {
        "id": "30b848f47c56dec0",
        "type": "leaf",
        "state": {
          "type": "review-queue-list-view",
          "state": {},
          "icon": "SpacedRepIcon",
          "title": "Notes Review Queue"
        }
      }
    ],
    "currentTab": 5
  },
  "left-ribbon": {
    "hiddenItems": {
      "switcher:Open quick switcher": false,
      "graph:Open graph view": false,
      "canvas:Create new canvas": false,
      "command-palette:Open command palette": false,
      "markdown-importer:Open format converter": false,
      "random-note:Open random note": false,
      "workspaces:Manage workspace layouts": false,
      "obsidian-spaced-repetition:Review flashcards": false,
      "templater-obsidian:Templater": false,
      "table-editor-obsidian:Advanced Tables Toolbar": false,
      "periodic-notes:Open today": false
    }
  },
  "active": "f1df0463a49d1aa9",
  "lastOpenFiles": [
    "Zen/Group theory MOC.md",
    "Zen/Conjugation by an element.md",
    "Zen/Automorphism.md",
    "Zen/TV show database.md",
    "Sources/$Black Doves.md",
    "Zen/Semisimple module.md",
    "Zen/Natural Heisenberg algebras.md",
    "Zen/Virasoro algebra.md",
    "Zen/Witt algebra.md",
    "Zen/Heisenberg module.md",
    "Zen/Modules of a Heisenberg algebra.md",
    "Zen/Heisenberg algebra.md",
    "Degree operator on formal sum over a vector space.md",
    "Zen/Degree operator.md",
    "Formal delta.md",
    "Zen/Formal sums over endomorphisms.md",
    "Zen/Summable endomorphisms.md",
    "Formal series over an (un)twisted affine Lie algebra.md",
    "Zen/Liar paradox.md",
    "Zen/Hypothetical proposition.md",
    "Zen/ZF.md",
    "Zen/Axiom of Foundation.md",
    "Zen/Axiom Schema of Replacement.md",
    "Zen/Axiom of Infinity.md",
    "Zen/Powerset Axiom.md",
    "Zen/Specification Axiom Schema.md",
    "Bin",
    "Bin/Templates",
    "Bins/Attachments/natural transformation commutative diagram.png",
    "Zen/Space.canvas",
    "Bins/Scripts/Templater/musedata copy.js",
    "Bins/Attachments/Gaußian pillbox.png",
    "quiver.sty",
    "Bins/Attachments/tangent space.png",
    "export_part.yaml",
    "Bins/Attachments/real submanifold.png",
    "Bins/Attachments/ExampleLinear_ManimCE_v0.18.1.gif",
    "Bins/Attachments/ExampleLinearBasis_ManimCE_v0.18.1.gif",
    "Bins/Attachments/coproduct topology universal construction (bradley).png",
    "Long",
    "Bins/Attachments/HRDiagram.png",
    "Bins/Attachments/@strogatzNonlinearDynamicsChaos2024_5.2.8.png",
    "Bins/Attachments/protostars moving onto the main sequence.png",
    "doi.org",
    "doi.org/10.1080",
    "Lecture notes/MAT-65-05",
    "Lecture notes",
    "Space.canvas",
    "Untitled.canvas"
  ]
}